Workbook

Sheet Pivot Table
A2: E-COMMERCE SALES REPORT
A4: YEARLY SALES | D4: SALES BY COUPON | G4: PRODUCT SALES
A5: Date | B5: Total Sales | D5: Coupon | E5: Sales | G5: Products | H5: No. of Products | I5: Sum of TotalPrice | K5: INSIGHTS
A6: 2023 | B6: 552643.24 | D6: FREESHIP | E6: 335036.99 | G6: Chair | H6: 562 | I6: 195620.11 | K6: TOTAL REVENUE | L6: 12647462
A7: 2024 | B7: 480235.87 | D7: NO COUPON | E7: 322401.41 | G7: Desk | H7: 508 | I7: 167459.93 | K7: TOTAL ITEMS | L7: 3535
A8: 2025 | B8: 231882.85 | D8: SAVE10 | E8: 304840.02 | G8: Laptop | H8: 535 | I8: 192126.56 | K8: MAX ITEMS SOLD | L8: 5
A9: Grand Total | B9: 1264762 | D9: WINTER15 | E9: 302483.54 | G9: Monitor | H9: 480 | I9: 175651.41 | K9: MIN ITEMS SOLD | L9: 1
G10: Phone | H10: 411 | I10: 151722.39 | K10: TOTAL ORDERS | L10: 1200
G11: Printer | H11: 542 | I11: 195612.61
A12: SALES PER MODE OF PAYMENT | D12: PRODUCT STATUS | G12: Tablet | H12: 497 | I12: 186568.95
A13: Payment Mode | B13: Sales | D13: Order Status | E13: No. of Products
A14: Credit Card | B14: 263847.63 | D14: Cancelled | E14: 759
A15: Online | B15: 262442.94 | D15: Delivered | E15: 690 | G15: DESCRIPTIVE ANALYSIS
A16: Cash | B16: 259786.29 | D16: Pending | E16: 724 | G16: METRIC | H16: QUANTITY | I16: UNIT PRICE | J16: TOTAL PRICE
A17: Gift Card | B17: 246323.92 | D17: Returned | E17: 682 | G17: Sum | H17: =SUM('Cleaned Data'!E2:E1201) -> 3535 | I17: =SUM('Cleaned Data'!F2:F1201) -> 427695.3 | J17: =SUM('Cleaned Data'!N2:N1201) -> 1264762
A18: Debit Card | B18: 232361.18 | D18: Shipped | E18: 680 | G18: Mean | H18: =AVERAGE('Cleaned Data'!E2:E1201) -> 2.9458333 | I18: =I17/I23 -> 356.41275 | J18: =AVERAGE('Cleaned Data'!N2:N1201) -> 1053.9683
D19: Grand Total | E19: 3535 | G19: Mode | H19: =MODE('Cleaned Data'!E2:E1201) -> 1 | I19: =MODE('Cleaned Data'!F2:F1201) -> 127.18 | J19: =MODE('Cleaned Data'!N2:N1201) -> 635.9
G20: Median | H20: =MEDIAN('Cleaned Data'!E2:E1201) -> 3 | I20: =MEDIAN('Cleaned Data'!F2:F1201) -> 364.21 | J20: =MEDIAN('Cleaned Data'!N2:N1201) -> 823.615
A21: SALES PER AFFILIATE | G21: Min | H21: =MIN('Cleaned Data'!E2:E1201) -> 1 | I21: =MIN('Cleaned Data'!F2:F1201) -> 11.39 | J21: =MIN('Cleaned Data'!N2:N1201) -> 11.39
A22: Source | B22: Sales | G22: Max | H22: =MAX('Cleaned Data'!E2:E1201) -> 5 | I22: =MAX('Cleaned Data'!F2:F1201) -> 699.93 | J22: =MAX('Cleaned Data'!N2:N1201) -> 3456.4
A23: Instagram | B23: 275285.45 | G23: Count | H23: =COUNT('Cleaned Data'!E2:E1201) -> 1200 | I23: =COUNT('Cleaned Data'!F2:F1201) -> 1200 | J23: =COUNT('Cleaned Data'!N2:N1201) -> 1200
A24: Email | B24: 261808.55 | G24: Standard Dev | H24: =STDEV('Cleaned Data'!E2:E1201) -> 1.4075571 | I24: =STDEV('Cleaned Data'!F2:F1201) -> 197.17715 | J24: =STDEV('Cleaned Data'!N2:N1201) -> 819.85656
A25: Google | B25: 250441.48
A26: Facebook | B26: 250410.9
A27: Referral | B27: 226815.58

Sheet Cleaned Data
A1: OrderID | B1: Date | C1: CustomerID | D1: Product | E1: Quantity | F1: UnitPrice | G1: ShippingAddress | H1: PaymentMethod | I1: OrderStatus | J1: TrackingNumber | K1: ItemsInCart | L1: CouponCode | M1: ReferralSource | N1: TotalPrice
A2: ORD200000 | B2: 44930 | C2: C72649 | D2: Monitor | E2: 5 | F2: 570.62 | G2: 928 Main St | H2: Debit Card | I2: Shipped | J2: TRK37947903 | K2: 7 | L2: SAVE10 | M2: Instagram | N2: 2853.1
A3: ORD200001 | B3: 45527 | C3: C75739 | D3: Phone | E3: 2 | F3: 151.35 | G3: 823 Main St | H3: Online | I3: Shipped | J3: TRK91186779 | K3: 3 | L3: SAVE10 | M3: Referral | N3: 302.7
A4: ORD200002 | B4: 45349 | C4: C81728 | D4: Tablet | E4: 5 | F4: 550.68 | G4: 512 Main St | H4: Credit Card | I4: Cancelled | J4: TRK42903982 | K4: 8 | L4: FREESHIP | M4: Email | N4: 2753.4
A5: ORD200003 | B5: 45214 | C5: C33540 | D5: Chair | E5: 1 | F5: 273.19 | G5: 275 Main St | H5: Debit Card | I5: Returned | J5: TRK62788070 | K5: 5 | L5: SAVE10 | M5: Facebook | N5: 273.19
A6: ORD200004 | B6: 45785 | C6: C81840 | D6: Printer | E6: 4 | F6: 626.01 | G6: 668 Main St | H6: Online | I6: Delivered | J6: TRK29241424 | K6: 8 | L6: SAVE10 | M6: Email | N6: 2504.04
A7: ORD200005 | B7: 45222 | C7: C37249 | D7: Phone | E7: 2 | F7: 245.86 | G7: 934 Main St | H7: Credit Card | I7: Shipped | J7: TRK72976927 | K7: 4 | L7: SAVE10 | M7: Instagram | N7: 491.72
A8: ORD200006 | B8: 45825 | C8: C83492 | D8: Laptop | E8: 1 | F8: 664.42 | G8: 986 Main St | H8: Gift Card | I8: Returned | J8: TRK96417362 | K8: 6 | L8: SAVE10 | M8: Facebook | N8: 664.42
A9: ORD200007 | B9: 45058 | C9: C41460 | D9: Monitor | E9: 5 | F9: 149.55 | G9: 706 Main St | H9: Cash | I9: Shipped | J9: TRK78809193 | K9: 9 | L9: FREESHIP | M9: Facebook | N9: 747.75
A10: ORD200008 | B10: 45749 | C10: C26817 | D10: Phone | E10: 2 | F10: 134.28 | G10: 904 Main St | H10: Gift Card | I10: Cancelled | J10: TRK61042692 | K10: 2 | L10: NO COUPON | M10: Email | N10: 268.56
A11: ORD200009 | B11: 45251 | C11: C31946 | D11: Desk | E11: 4 | F11: 509.38 | G11: 102 Main St | H11: Credit Card | I11: Shipped | J11: TRK33478363 | K11: 6 | L11: SAVE10 | M11: Google | N11: 2037.52
A12: ORD200010 | B12: 45289 | C12: C43443 | D12: Tablet | E12: 5 | F12: 625.97 | G12: 333 Main St | H12: Credit Card | I12: Returned | J12: TRK98859248 | K12: 9 | L12: WINTER15 | M12: Instagram | N12: 3129.85
A13: ORD200011 | B13: 45339 | C13: C93861 | D13: Monitor | E13: 3 | F13: 49.14 | G13: 831 Main St | H13: Online | I13: Returned | J13: TRK48234646 | K13: 7 | L13: SAVE10 | M13: Email | N13: 147.42
... A1201: ORD201199 | B1201: 45088 | C1201: C57502 | D1201: Tablet | E1201: 4 | F1201: 560.58 | G1201: 201 Main St | H1201: Gift Card | I1201: Returned | J1201: TRK51116746 | K1201: 6 | L1201: SAVE10 | M1201: Referral | N1201: 2242.32
